PyTaskFarmer-0.1.0.data/scripts/pytaskfarmer.py
taskfarmer/__init__.py
taskfarmer/atlas.py
taskfarmer/runners.py
taskfarmer/task.py
PyTaskFarmer-0.1.0.dist-info/METADATA
PyTaskFarmer-0.1.0.dist-info/WHEEL
PyTaskFarmer-0.1.0.dist-info/top_level.txt
PyTaskFarmer-0.1.0.dist-info/RECORD
