Metadata-Version: 2.1
Name: PyTaskFarmer
Version: 0.1.0
Summary: Simple task farmer using file locks to syncrhonize among multiple nodes.
Home-page: https://gitlab.cern.ch/berkeleylab/pytaskfarmer
License: UNKNOWN
Platform: UNKNOWN
